lzhfreshrssapi/__init__.py
lzhfreshrssapi-0.2.1.dist-info/METADATA
lzhfreshrssapi-0.2.1.dist-info/WHEEL
lzhfreshrssapi-0.2.1.dist-info/top_level.txt
lzhfreshrssapi-0.2.1.dist-info/RECORD
