Metadata-Version: 2.4
Name: lzhfreshrssapi
Version: 0.2.1
Summary: 获取`FreshRSS`数据库中对应`url`的订阅源中已有的`guid`的集合
Author-email: lzh <zhhtdm@hotmail.com>
License: MIT
Project-URL: Homepage, https://github.com/zhhtdm/freshrss-api
Project-URL: Repository, https://github.com/zhhtdm/freshrss-api
Requires-Python: >=3.7
Requires-Dist: asyncpg
Requires-Dist: aiohttp
